vkton/__init__.py
vkton/bot.py
vkton/classes.py
vkton/config.py
vkton/errors.py
vkton/objects.py
vkton/ui.py
vkton-0.2.11.dist-info/METADATA
vkton-0.2.11.dist-info/WHEEL
vkton-0.2.11.dist-info/RECORD
