Metadata-Version: 2.1
Name: vkton
Version: 0.2.11
Summary: Модуль на Python позволяющий быстро создавать VK ботов
License: MIT
Author: Alex Lovser
Author-email: tabalex2005@gmail.com
Requires-Python: >=3.10,<4.0
Classifier: License :: OSI Approved :: MIT License
Classifier: Programming Language :: Python :: 3
Classifier: Programming Language :: Python :: 3.10
Classifier: Programming Language :: Python :: 3.11
Requires-Dist: pillow (>=10.0.0,<11.0.0)
Requires-Dist: uuid (>=1.30,<2.0)
Requires-Dist: vk-api (>=11.9.9,<12.0.0)
